tutti/__init__.py
tutti/asyncio.py
tutti/base.py
tutti/configuration.py
tutti/py.typed
tutti/sync.py
tutti/backends/redis/__init__.py
tutti/backends/redis/asyncio.py
tutti/backends/redis/connection.py
tutti/backends/redis/sync.py
tutti/backends/redis/types.py
tutti/backends/redis/utils.py
tutti-1.0.0.dist-info/METADATA
tutti-1.0.0.dist-info/WHEEL
tutti-1.0.0.dist-info/licenses/LICENSE
tutti-1.0.0.dist-info/RECORD
